MANIFEST.in
README.md
setup.py
src/pydrummer/__init__.py
src/pydrummer/config.py
src/pydrummer/player.py
src/pydrummer/settings.py
src/pydrummer.egg-info/PKG-INFO
src/pydrummer.egg-info/SOURCES.txt
src/pydrummer.egg-info/dependency_links.txt
src/pydrummer.egg-info/requires.txt
src/pydrummer.egg-info/top_level.txt
src/pydrummer/models/__init__.py
src/pydrummer/models/clip.py
src/pydrummer/models/mix.py
src/pydrummer/models/sequence.py
src/pydrummer/models/song.py
src/pydrummer/models/sound.py
src/pydrummer/samples/__init__.py
src/pydrummer/samples/808/clap.wav
src/pydrummer/samples/808/clave.wav
src/pydrummer/samples/808/congahi.wav
src/pydrummer/samples/808/congalo.wav
src/pydrummer/samples/808/congamid.wav
src/pydrummer/samples/808/cowbell.wav
src/pydrummer/samples/808/cymbal.wav
src/pydrummer/samples/808/hhclosed.wav
src/pydrummer/samples/808/hhopen.wav
src/pydrummer/samples/808/kick.wav
src/pydrummer/samples/808/kick2.wav
src/pydrummer/samples/808/kick3.wav
src/pydrummer/samples/808/kickrr.wav
src/pydrummer/samples/808/kickrr2.wav
src/pydrummer/samples/808/kickrr3.wav
src/pydrummer/samples/808/maracas.wav
src/pydrummer/samples/808/rimshot.wav
src/pydrummer/samples/808/snare.wav
src/pydrummer/samples/808/snare2.wav
src/pydrummer/samples/808/snare3.wav
src/pydrummer/samples/808/tomhi.wav
src/pydrummer/samples/808/tomlo.wav
src/pydrummer/samples/808/tommid.wav