Metadata-Version: 1.0
Name: pydrummer
Version: 0.1.dev0
Summary: a minimal drum machine
Home-page: http://github.com/allieoop/pydrummer
Author: Allie Crevier
Author-email: okay@allie.is
License: MIT
Platform: UNKNOWN
